{
  "title": "How do you manage cloud-native applications across hybrid cloud environments?",
  "description": "A hybrid cloud environment integrates public cloud, private cloud, and on-premises resources to provide flexible deployment and resource optimization; cloud-native applications are based on containeri",
  "category": "Multi-Cloud and Hybrid Cloud Deployment",
  "keywords": [
    "Cloud-Native",
    "Lakehouse",
    "IT Infrastructure",
    "High Performance",
    "DevOps"
  ],
  "content": "A hybrid cloud environment integrates public cloud, private cloud, and on-premises resources to provide flexible deployment and resource optimization; cloud-native applications are based on containerization and microservices, featuring elastic scalability and high availability. Its management is crucial to ensure consistency and compliance, suitable for cross-cloud elastic deployment scenarios such as global e-commerce or financial services, supporting business agility and risk control.\n\nCore components include Kubernetes orchestration for container scheduling, service meshes (e.g., Istio) for handling cross-cloud communication, and CI/CD pipelines for automated deployment; features emphasize self-healing and consistent management across environments. Practical applications use tools like Anthos or OpenShift to uniformly monitor resources, enhance application resilience and disaster recovery capabilities, and reduce vendor lock-in effects on multi-cloud strategies.\n\nImplementation steps are as follows: containerize applications and deploy Kubernetes clusters; configure a multi-cloud management platform to achieve resource orchestration; integrate security and compliance policies; deploy monitoring and logging tools. Typical scenarios include hybrid load balancing or edge computing deployment, with business value driving cost optimization, high response speed, and compliance assurance, such as reducing time-to-market by 50%."
}