{
  "title": "How do you automate end-to-end testing in CI/CD pipelines?",
  "description": "Automating end-to-end (E2E) testing in a CI/CD pipeline refers to simulating real user operations through tools and scripts to verify the entire application's functional workflows. This is crucial as ",
  "category": "Continuous Integration and Continuous Deployment",
  "keywords": [
    "Kubernetes (K8s)",
    "Sealos",
    "Lakehouse",
    "Cloud-Native",
    "Open-Source Cloud"
  ],
  "content": "Automating end-to-end (E2E) testing in a CI/CD pipeline refers to simulating real user operations through tools and scripts to verify the entire application's functional workflows. This is crucial as it ensures high quality is maintained during rapid software delivery cycles, prevents production defects, and is applied in agile development and cloud-native environments to enhance software reliability.\n\nCore components include E2E testing frameworks (such as Selenium or Cypress) for creating test scripts that cover user paths from the interface to the backend. The principle is to integrate testing into CI/CD tools (such as Jenkins or GitLab CI), add independent testing stages, and run them automatically after each code commit. In practical applications, this reduces the need for manual testing, improves coverage, directly impacts DevOps efficiency, shortens release cycles, and enhances team confidence in deliveries.\n\nImplementation steps include: selecting testing tools and writing test cases covering key user scenarios; configuring the CI/CD pipeline to trigger test tasks after builds; setting up failure notification and reporting mechanisms. Typical business values are automated defect detection, reduced maintenance costs, accelerated product iteration, and improved user experience."
}