{
  "title": "How do you ensure quality and reliability with CI/CD in cloud-native environments?",
  "description": "In cloud-native environments, Continuous Integration/Continuous Deployment (CI/CD) ensures application quality and reliability by automating software build, testing, and deployment processes. This is ",
  "category": "Continuous Integration and Continuous Deployment",
  "keywords": [
    "Containerization",
    "Sealos",
    "Cluster Management",
    "Open-Source Cloud",
    "Cloud Operating System"
  ],
  "content": "In cloud-native environments, Continuous Integration/Continuous Deployment (CI/CD) ensures application quality and reliability by automating software build, testing, and deployment processes. This is crucial in microservices, containerization, and Kubernetes management scenarios, supporting rapid iteration, high availability, and reducing the risk of human errors.\n\nCore components include source code management (e.g., Git), automated build tools (e.g., Jenkins or GitHub Actions), testing frameworks (unit, integration, end-to-end testing), and deployment pipelines (e.g., using Argo CD or Helm). The principle is to detect issues through frequent code merging and early testing, combined with cloud-native features such as elastic scaling and health checks, to achieve seamless updates. In practical applications, CI/CD enhances system resilience, reduces downtime, and has a significant impact on businesses by enabling agile development and reliable delivery.\n\nImplementation steps: First, automatically build and test after a change is triggered in the code repository; second, deploy to the pre-production environment for verification; finally, automatically push to the production environment. Typical scenarios include the GitOps model to ensure configuration consistency, and business values include accelerating release cycles, enhancing user experience, reducing costs, thereby improving market competitiveness."
}