{
  "title": "How do cloud-native environments support multi-cloud deployments?",
  "description": "Cloud-native environments effectively support multi-cloud deployment through standardized technology stacks and dynamic orchestration capabilities. Their core is to eliminate infrastructure difference",
  "category": "Cloud-Native Development Environments",
  "keywords": [
    "High Performance",
    "Cloud-Native",
    "Kubernetes (K8s)",
    "Containerization",
    "Data Center (DC)"
  ],
  "content": "Cloud-native environments effectively support multi-cloud deployment through standardized technology stacks and dynamic orchestration capabilities. Their core is to eliminate infrastructure differences, enabling applications to seamlessly migrate and scale across multiple cloud platforms. This capability is crucial for avoiding vendor lock-in, enhancing business continuity, and optimizing costs, especially suitable for enterprise scenarios requiring cross-regional compliance, disaster recovery redundancy, or elastic scaling.\n\nKey technical supports include: 1) Containerization (such as Docker) to package applications and dependencies, ensuring environmental consistency; 2) Kubernetes provides a unified orchestration layer, abstracting underlying cloud resources and automatically scheduling Pods to different cloud nodes; 3) Service mesh (such as Istio) enables cross-cloud service discovery and traffic management; 4) CI/CD pipelines and GitOps practices realize automated deployment and version control of multi-cloud applications. These components together build an infrastructure-agnostic application management plane.\n\nWhen implementing multi-cloud deployment: first, microservice-oriented applications and package them into containers; second, use Kubernetes Federation or multi-cluster management tools (such as Karmada) to uniformly manage clusters distributed across different clouds; then configure cross-cloud communication and security policies through service mesh; finally, rely on DevOps toolchains to achieve continuous delivery. This solution significantly improves system availability (single cloud failure does not affect the overall situation), realizes cost optimization of cloud resources (on-demand scheduling to low-cost regions), and accelerates global business deployment."
}