{
  "title": "How do you ensure high availability of monitoring tools in cloud-native applications?",
  "description": "In cloud-native applications, the high availability of monitoring tools refers to their ability to continue operating during failures, ensuring real-time collection of performance data to avoid blind ",
  "category": "Monitoring and Observability",
  "keywords": [
    "Sealos",
    "Kubernetes (K8s)",
    "Application Deployment",
    "Cloud Platform",
    "High Performance"
  ],
  "content": "In cloud-native applications, the high availability of monitoring tools refers to their ability to continue operating during failures, ensuring real-time collection of performance data to avoid blind spots. This is crucial for rapid fault detection and business continuity, especially enhancing system reliability in microservice and distributed scenarios.\n\nThe core includes redundant deployment, load balancing, and automatic failover. Manage and deploy multiple replicas through Kubernetes, achieve data consistency using persistent storage and health checks, and integrate solutions such as Prometheus clusters or Thanos. In practical applications, it reduces monitoring interruptions, enhances system stability, and affects operational efficiency and alert response speed.\n\nImplementation steps: 1) Design a redundant architecture, such as deploying multiple monitoring instances; 2) Configure load balancing and service discovery; 3) Use data redundancy and backup strategies; 4) Automate deployment and update processes. Typical scenarios include running Grafana HA in Kubeless or OpenShift environments. The business value lies in minimizing downtime risks, ensuring continuous insights, improving user satisfaction, and supporting SLA compliance."
}