{
  "title": "How does automated deployment help in managing application lifecycle across multiple environments?",
  "description": "Automated deployment is the process of automatically executing code releases through tools and scripts, significantly improving the efficiency of application lifecycle management across development, t",
  "category": "Automated Deployment",
  "keywords": [
    "One-Click Deployment",
    "High Performance",
    "Cloud-Native",
    "Application Deployment",
    "Containerization"
  ],
  "content": "Automated deployment is the process of automatically executing code releases through tools and scripts, significantly improving the efficiency of application lifecycle management across development, testing, and production environments. It is indispensable in DevOps practices, supporting efficient iteration and environmental consistency, and is widely used in multi-cloud and hybrid cloud scenarios to reduce the risk of human error.\n\nThe core components include continuous integration/continuous deployment (CI/CD) pipelines, infrastructure as code (such as Terraform), and environment configuration management. The principle is that automated scripts ensure the standardization of the deployment process, enabling rapid migration, testing, and rollback. In practical applications, it uniformly manages multiple environments, reduces errors, accelerates releases, and improves the productivity of development teams.\n\nDuring implementation, first establish CI/CD pipeline tools (such as Jenkins or GitHub Actions), and integrate automated testing and environment templating. Typical scenarios include seamless transition from development to production, and business value is reflected in shortening time to market, enhancing system reliability, optimizing resource utilization, and reducing costs and increasing efficiency."
}