{
  "title": "How does automation help manage the complexity of scaling cloud applications?",
  "description": "Automation handles the complexity of cloud application scaling by dynamically adjusting resource allocation, which is key in responding to sudden traffic surges, maintaining performance, and optimizin",
  "category": "Automated Deployment",
  "keywords": [
    "Private Cloud",
    "Data Center (DC)",
    "Containerization",
    "IT Infrastructure",
    "One-Click Deployment"
  ],
  "content": "Automation handles the complexity of cloud application scaling by dynamically adjusting resource allocation, which is key in responding to sudden traffic surges, maintaining performance, and optimizing costs. Its importance lies in real-time response to changes without manual intervention, ensuring high availability and responsiveness of applications, making it suitable for scenarios with significant traffic fluctuations and distinct business peaks (e.g., e-commerce promotions).\n\nIts core is a policy-driven closed-loop control system: after defining scaling metrics (such as CPU utilization, request rate) and scaling rules, monitoring components collect data in real time, the analysis engine compares against the rules, and automatically triggers resource scheduling (such as increasing or decreasing the number of Kubernetes Pods or virtual machine instances). This integrates Infrastructure as Code (IaC) to achieve environmental consistency and reduces decision latency and error risks through predefined policies.\n\nImplementation typically follows these steps: defining clear scaling metrics and target thresholds; selecting tools (such as Kubernetes HPA, cloud service provider Auto Scaling); configuring automation policies (minimum/maximum instance count, cooldown period); continuously monitoring and optimizing rules. The business value lies in significantly reducing operational overhead, avoiding downtime risks caused by manual scaling, and optimizing cloud computing resource costs (pay-as-you-go usage)."
}