{
  "title": "How do you implement service discovery in microservices environments?",
  "description": "Service discovery in a microservices environment is a core mechanism that ensures dynamic service instances can locate each other. It addresses the issue of IP/port changes caused by instance scaling",
  "category": "Microservices Architecture",
  "keywords": [
    "Lakehouse",
    "IT Infrastructure",
    "Cloud Platform",
    "High Performance",
    "Containerization"
  ],
  "content": "Service discovery in a microservices environment is a core mechanism that ensures dynamic service instances can locate each other. It addresses the issue of IP/port changes caused by instance scaling, failures, and restarts, making it crucial for building resilient and manageable applications. It is applied in modern cloud-native systems such as the backend of e-commerce platforms.\n\nIts core components include service registries (e.g., Consul, Zookeeper, Kubernetes' built-in etcd) and service client query mechanisms. When a microservice instance starts, it automatically registers its metadata with the service registry. Other services (or gateways) query the list of available instances from this registry based on service names or tags. Common implementation patterns include client-side discovery (where applications actively query) and server-side discovery (via load balancer proxies). This significantly simplifies network configuration and improves the overall resilience and observability of the system.\n\nThe implementation steps are as follows: After a service instance starts, it calls the registration API to register its information with the service registry. The service consumer (client) queries the registry for the list of available instances of the target service and their network addresses. The client intelligently routes requests by combining the query results with built-in load balancing (e.g., Netflix Ribbon). This process ensures continuous discovery, failover, and resilient service upgrades, supporting automated scaling and complex dependency management."
}